pydeye/__init__.py
pydeye/exceptions.py
pydeye/helper.py
pydeye/interfaces/ModbusTCP.py
pydeye/interfaces/__init__.py
pydeye/inverters/__init__.py
pydeye/inverters/base_inverter.py
pydeye/inverters/deye_SUN12KEU.py
pydeye/measurements.py
pydeye-0.0.13.dist-info/METADATA
pydeye-0.0.13.dist-info/WHEEL
pydeye-0.0.13.dist-info/RECORD
